{
  "project_info": {
    "project_number": "206526653884",
    "project_id": "krishishop-c1de8",
    "storage_bucket": "krishishop-c1de8.appspot.com"
  },
  "client": [
    {
      "client_info": {
        "mobilesdk_app_id": "1:206526653884:android:385ee322715a483e6877b9",
        "android_client_info": {
          "package_name": "com.example.krishishop"
        }
      },
      "oauth_client": [
        {
          "client_id": "206526653884-shbvv3q0pbk739gs0lvh4g7ko9n9eim5.apps.googleusercontent.com",
          "client_type": 3
        }
      ],
      "api_key": [
        {
          "current_key": "AIzaSyBv9Fqr5LSIhzEQ98X9A1RjvN7XnblL7m4"
        }
      ],
      "services": {
        "appinvite_service": {
          "other_platform_oauth_client": [
            {
              "client_id": "206526653884-shbvv3q0pbk739gs0lvh4g7ko9n9eim5.apps.googleusercontent.com",
              "client_type": 3
            }
          ]
        }
      }
    }
  ],
  "configuration_version": "1"
}